{"version":3,"kind":"Article","sha256":"9f6a0436505014beb012e34a9e9e1d77363c6e61902310709f57c68166e8eaf5","slug":"data","location":"/data.md","dependencies":[],"frontmatter":{"title":"Data Sources","content_includes_title":false,"authors":[{"nameParsed":{"given":"PolicyEngine","family":"Team","literal":"PolicyEngine Team"},"name":"PolicyEngine Team","id":"contributors-myst-generated-uid-0"}],"github":"https://github.com/policyengine/policyengine-us-data","copyright":"2024","source_url":"https://github.com/policyengine/policyengine-us-data/blob/main/docs/data.md","edit_url":"https://github.com/policyengine/policyengine-us-data/edit/main/docs/data.md","exports":[{"format":"md","filename":"data.md","url":"/policyengine-us-data/build/data-ee969ac2c6a29d51052a26ad1290334d.md"}]},"mdast":{"type":"root","children":[{"type":"block","children":[{"type":"paragraph","position":{"start":{"line":3,"column":1},"end":{"line":4,"column":1}},"children":[{"type":"text","value":"Our methodology combines two primary data sources with calibration targets from administrative\nsources.","position":{"start":{"line":3,"column":1},"end":{"line":3,"column":1}},"key":"lKU3We51Eq"}],"key":"dNqypDnqwL"},{"type":"heading","depth":2,"position":{"start":{"line":6,"column":1},"end":{"line":6,"column":1}},"children":[{"type":"text","value":"Data vintages","position":{"start":{"line":6,"column":1},"end":{"line":6,"column":1}},"key":"RdTS5XwjJq"}],"identifier":"data-vintages","label":"Data vintages","html_id":"data-vintages","implicit":true,"key":"KltsxmMTZW"},{"type":"table","position":{"start":{"line":8,"column":1},"end":{"line":15,"column":1}},"children":[{"type":"tableRow","position":{"start":{"line":8,"column":1},"end":{"line":8,"column":1}},"children":[{"type":"tableCell","header":true,"position":{"start":{"line":8,"column":1},"end":{"line":8,"column":1}},"children":[{"type":"text","value":"Dataset","position":{"start":{"line":8,"column":1},"end":{"line":8,"column":1}},"key":"nbEVlCmLd7"}],"key":"oh4swgARCP"},{"type":"tableCell","header":true,"position":{"start":{"line":8,"column":1},"end":{"line":8,"column":1}},"children":[{"type":"text","value":"Vintage","position":{"start":{"line":8,"column":1},"end":{"line":8,"column":1}},"key":"npf4n235fM"}],"key":"SIkZBt4Fjq"},{"type":"tableCell","header":true,"position":{"start":{"line":8,"column":1},"end":{"line":8,"column":1}},"children":[{"type":"text","value":"Notes","position":{"start":{"line":8,"column":1},"end":{"line":8,"column":1}},"key":"aAHWtlxERQ"}],"key":"y9GH138OTy"}],"key":"O0pbuXYo1e"},{"type":"tableRow","position":{"start":{"line":10,"column":1},"end":{"line":10,"column":1}},"children":[{"type":"tableCell","position":{"start":{"line":10,"column":1},"end":{"line":10,"column":1}},"children":[{"type":"text","value":"CPS ASEC","position":{"start":{"line":10,"column":1},"end":{"line":10,"column":1}},"key":"rqMIubikgK"}],"key":"N70BYUfoBu"},{"type":"tableCell","position":{"start":{"line":10,"column":1},"end":{"line":10,"column":1}},"children":[{"type":"text","value":"2024 (income year 2023)","position":{"start":{"line":10,"column":1},"end":{"line":10,"column":1}},"key":"Apag3OWuu0"}],"key":"J52Zyjn0Tx"},{"type":"tableCell","position":{"start":{"line":10,"column":1},"end":{"line":10,"column":1}},"children":[{"type":"text","value":"Base microdata; pipeline ages values to target policy year","position":{"start":{"line":10,"column":1},"end":{"line":10,"column":1}},"key":"ZIuh9z5370"}],"key":"z1kQpR6VVZ"}],"key":"SFNqfSpoxY"},{"type":"tableRow","position":{"start":{"line":11,"column":1},"end":{"line":11,"column":1}},"children":[{"type":"tableCell","position":{"start":{"line":11,"column":1},"end":{"line":11,"column":1}},"children":[{"type":"text","value":"IRS PUF","position":{"start":{"line":11,"column":1},"end":{"line":11,"column":1}},"key":"pM9dSJUk0v"}],"key":"lGxTboQg4R"},{"type":"tableCell","position":{"start":{"line":11,"column":1},"end":{"line":11,"column":1}},"children":[{"type":"text","value":"2015","position":{"start":{"line":11,"column":1},"end":{"line":11,"column":1}},"key":"GFQJX00qWW"}],"key":"eJbP9YXD2q"},{"type":"tableCell","position":{"start":{"line":11,"column":1},"end":{"line":11,"column":1}},"children":[{"type":"text","value":"Pipeline ages values to target policy year using income growth indices","position":{"start":{"line":11,"column":1},"end":{"line":11,"column":1}},"key":"G3A49TLZsu"}],"key":"FecY3NrLhD"}],"key":"gADNJ5u1bj"},{"type":"tableRow","position":{"start":{"line":12,"column":1},"end":{"line":12,"column":1}},"children":[{"type":"tableCell","position":{"start":{"line":12,"column":1},"end":{"line":12,"column":1}},"children":[{"type":"text","value":"ACS","position":{"start":{"line":12,"column":1},"end":{"line":12,"column":1}},"key":"dtuDijrzvn"}],"key":"wRJtjMF6yj"},{"type":"tableCell","position":{"start":{"line":12,"column":1},"end":{"line":12,"column":1}},"children":[{"type":"text","value":"2022","position":{"start":{"line":12,"column":1},"end":{"line":12,"column":1}},"key":"kXNMmAFlIS"}],"key":"aaKhIyNjRp"},{"type":"tableCell","position":{"start":{"line":12,"column":1},"end":{"line":12,"column":1}},"children":[{"type":"text","value":"Provides rent and real estate tax imputation targets","position":{"start":{"line":12,"column":1},"end":{"line":12,"column":1}},"key":"QGiZblP5WI"}],"key":"NgPwHd2uRy"}],"key":"zuP3LaLUfS"},{"type":"tableRow","position":{"start":{"line":13,"column":1},"end":{"line":13,"column":1}},"children":[{"type":"tableCell","position":{"start":{"line":13,"column":1},"end":{"line":13,"column":1}},"children":[{"type":"text","value":"SCF","position":{"start":{"line":13,"column":1},"end":{"line":13,"column":1}},"key":"zxtBRrVEcX"}],"key":"l4EuHqmf0x"},{"type":"tableCell","position":{"start":{"line":13,"column":1},"end":{"line":13,"column":1}},"children":[{"type":"text","value":"2022","position":{"start":{"line":13,"column":1},"end":{"line":13,"column":1}},"key":"jGTHMcpkas"}],"key":"qWzl5MLDfo"},{"type":"tableCell","position":{"start":{"line":13,"column":1},"end":{"line":13,"column":1}},"children":[{"type":"text","value":"Provides wealth and debt variable imputation targets","position":{"start":{"line":13,"column":1},"end":{"line":13,"column":1}},"key":"NitfxJBPG4"}],"key":"cKWo3mtPxN"}],"key":"O8CMXLTCfl"},{"type":"tableRow","position":{"start":{"line":14,"column":1},"end":{"line":14,"column":1}},"children":[{"type":"tableCell","position":{"start":{"line":14,"column":1},"end":{"line":14,"column":1}},"children":[{"type":"text","value":"SIPP","position":{"start":{"line":14,"column":1},"end":{"line":14,"column":1}},"key":"Hb3KfwGpPz"}],"key":"L56jgmlRr9"},{"type":"tableCell","position":{"start":{"line":14,"column":1},"end":{"line":14,"column":1}},"children":[{"type":"text","value":"2023","position":{"start":{"line":14,"column":1},"end":{"line":14,"column":1}},"key":"XpxgSQyCpE"}],"key":"r4DsBB7TYq"},{"type":"tableCell","position":{"start":{"line":14,"column":1},"end":{"line":14,"column":1}},"children":[{"type":"text","value":"Provides tip income and asset imputation targets","position":{"start":{"line":14,"column":1},"end":{"line":14,"column":1}},"key":"tkdOnusgX1"}],"key":"A9JSDThjQz"}],"key":"uDQJ95jrZM"},{"type":"tableRow","position":{"start":{"line":15,"column":1},"end":{"line":15,"column":1}},"children":[{"type":"tableCell","position":{"start":{"line":15,"column":1},"end":{"line":15,"column":1}},"children":[{"type":"text","value":"Calibration targets","position":{"start":{"line":15,"column":1},"end":{"line":15,"column":1}},"key":"LBVe0BY6R3"}],"key":"uuhC6Q8S4U"},{"type":"tableCell","position":{"start":{"line":15,"column":1},"end":{"line":15,"column":1}},"children":[{"type":"text","value":"Primarily 2023–2024","position":{"start":{"line":15,"column":1},"end":{"line":15,"column":1}},"key":"uHIpQdKY3z"}],"key":"jrFlyPCUfA"},{"type":"tableCell","position":{"start":{"line":15,"column":1},"end":{"line":15,"column":1}},"children":[{"type":"text","value":"Varies by source; see calibration data sources below","position":{"start":{"line":15,"column":1},"end":{"line":15,"column":1}},"key":"Vu2J4T40Mh"}],"key":"i25bp7Ncyn"}],"key":"e6WSUO5PWn"}],"key":"VFHKYfbJQ9"},{"type":"heading","depth":2,"position":{"start":{"line":17,"column":1},"end":{"line":17,"column":1}},"children":[{"type":"text","value":"Primary Data Sources","position":{"start":{"line":17,"column":1},"end":{"line":17,"column":1}},"key":"Jo648oMTSD"}],"identifier":"primary-data-sources","label":"Primary Data Sources","html_id":"primary-data-sources","implicit":true,"key":"gqrdXgeetA"},{"type":"heading","depth":3,"position":{"start":{"line":19,"column":1},"end":{"line":19,"column":1}},"children":[{"type":"text","value":"Current Population Survey (CPS)","position":{"start":{"line":19,"column":1},"end":{"line":19,"column":1}},"key":"DIwHsUF3sj"}],"identifier":"current-population-survey-cps","label":"Current Population Survey (CPS)","html_id":"current-population-survey-cps","implicit":true,"key":"fMdcg0qd3S"},{"type":"paragraph","position":{"start":{"line":21,"column":1},"end":{"line":23,"column":1}},"children":[{"type":"text","value":"The Current Population Survey Annual Social and Economic Supplement (ASEC) serves as our base\ndataset. The Census Bureau and Bureau of Labor Statistics jointly conduct the CPS ASEC, surveying\nhouseholds annually.","position":{"start":{"line":21,"column":1},"end":{"line":21,"column":1}},"key":"WbUpRtUNkY"}],"key":"cXHQjVNzlX"},{"type":"paragraph","position":{"start":{"line":25,"column":1},"end":{"line":31,"column":1}},"children":[{"type":"text","value":"The CPS provides features for microsimulation modeling. It offers a representative sample of US\nhouseholds with demographic information including age, education, race, and employment status. The\nsurvey captures family and household relationships through relationship codes that allow\nreconstruction of tax units and benefit units. Geographic identifiers down to the state level enable\nsubnational policy analysis. The survey includes questions about program participation in transfer\nprograms like SNAP, Medicaid, and housing assistance. The survey collects income data by source,\ndistinguishing between wages, self-employment, interest, dividends, and transfers.","position":{"start":{"line":25,"column":1},"end":{"line":25,"column":1}},"key":"XjLD5EiecI"}],"key":"TgDfTAFSL9"},{"type":"paragraph","position":{"start":{"line":33,"column":1},"end":{"line":37,"column":1}},"children":[{"type":"text","value":"The CPS faces limitations that necessitate enhancement. Income underreporting is severe at high\nincome levels ","position":{"start":{"line":33,"column":1},"end":{"line":33,"column":1}},"key":"cmeutsYO9B"},{"type":"citeGroup","kind":"parenthetical","children":[{"type":"cite","kind":"parenthetical","label":"rothbaum2021","identifier":"rothbaum2021","children":[{"type":"text","value":"Rothbaum & Bee, 2021","key":"GSeBdRPdTf"}],"enumerator":"1","key":"SaK7hzFeNh"}],"key":"NSrDOPjrdD"},{"type":"text","value":". The survey provides limited tax detail, lacking information on\nitemized deductions, tax credits, and capital gains realizations. The Census Bureau topcodes high\nincome values to protect confidentiality. The survey’s focus on cash income means it misses non-cash\ncompensation like employer-provided health insurance premiums.","position":{"start":{"line":33,"column":1},"end":{"line":33,"column":1}},"key":"sI6WFz5Lcr"}],"key":"NZ2FgW1qGF"},{"type":"heading","depth":3,"position":{"start":{"line":39,"column":1},"end":{"line":39,"column":1}},"children":[{"type":"text","value":"IRS Public Use File (PUF)","position":{"start":{"line":39,"column":1},"end":{"line":39,"column":1}},"key":"eFyhgTvUkI"}],"identifier":"irs-public-use-file-puf","label":"IRS Public Use File (PUF)","html_id":"irs-public-use-file-puf","implicit":true,"key":"Z1BXtaabWY"},{"type":"paragraph","position":{"start":{"line":41,"column":1},"end":{"line":42,"column":1}},"children":[{"type":"text","value":"The IRS Statistics of Income Public Use File contains tax return information that the IRS draws from\na stratified sample of individual income tax returns.","position":{"start":{"line":41,"column":1},"end":{"line":41,"column":1}},"key":"tB1e1RYfQD"}],"key":"h7TClSHWHK"},{"type":"paragraph","position":{"start":{"line":44,"column":1},"end":{"line":50,"column":1}},"children":[{"type":"text","value":"The PUF provides tax-related variables drawn from filed tax returns. It provides breakdowns of\nincome by source including wages, interest, dividends, capital gains, business income, and\nretirement distributions. The file includes itemized deductions such as mortgage interest, state and\nlocal taxes, and charitable contributions. The file includes tax credits that filers claim, from the\nearned income tax credit to education credits. The stratified sampling design oversamples\nhigh-income returns. Sampling weights allow researchers to produce population-representative\nestimates.","position":{"start":{"line":44,"column":1},"end":{"line":44,"column":1}},"key":"UWF5QDzP4A"}],"key":"OCueRIescN"},{"type":"paragraph","position":{"start":{"line":52,"column":1},"end":{"line":56,"column":1}},"children":[{"type":"text","value":"The PUF has limitations for policy analysis. The file contains minimal demographic information,\nlimited to filing status and exemptions claimed. The IRS removes geographic identifiers to protect\ntaxpayer privacy, which prevents state-level analysis. The population excludes non-filers. The PUF\nlacks household structure, preventing analysis of how tax policies interact with transfer programs\nthat operate at the household level.","position":{"start":{"line":52,"column":1},"end":{"line":52,"column":1}},"key":"vzNTe7pjpP"}],"key":"L71nmIJzJM"},{"type":"paragraph","position":{"start":{"line":58,"column":1},"end":{"line":61,"column":1}},"children":[{"type":"text","value":"The enhanced dataset retains the full CPS population, including non-filers. CPS copy-1 records keep\noriginal CPS income values for all households, covering non-filers and low-income households absent\nfrom PUF. Only copy-2 records replace income variables with PUF imputations and represent the filer\npopulation. This structure preserves non-filer coverage while enriching the tax detail for filers.","position":{"start":{"line":58,"column":1},"end":{"line":58,"column":1}},"key":"NfQTWDRDVk"}],"key":"PBZwpktmNV"},{"type":"heading","depth":2,"position":{"start":{"line":63,"column":1},"end":{"line":63,"column":1}},"children":[{"type":"text","value":"Additional Data Sources for Imputation","position":{"start":{"line":63,"column":1},"end":{"line":63,"column":1}},"key":"GN3cMBKZFw"}],"identifier":"additional-data-sources-for-imputation","label":"Additional Data Sources for Imputation","html_id":"additional-data-sources-for-imputation","implicit":true,"key":"G8Yf4r1ldG"},{"type":"paragraph","position":{"start":{"line":65,"column":1},"end":{"line":66,"column":1}},"children":[{"type":"text","value":"Beyond the PUF, we incorporate data from three additional surveys to impute specific variables\nmissing from the CPS:","position":{"start":{"line":65,"column":1},"end":{"line":65,"column":1}},"key":"UzTbkdS9Ul"}],"key":"vtrlaXyeKV"},{"type":"heading","depth":3,"position":{"start":{"line":68,"column":1},"end":{"line":68,"column":1}},"children":[{"type":"text","value":"Survey of Income and Program Participation (SIPP)","position":{"start":{"line":68,"column":1},"end":{"line":68,"column":1}},"key":"uPKrseSuHE"}],"identifier":"survey-of-income-and-program-participation-sipp","label":"Survey of Income and Program Participation (SIPP)","html_id":"survey-of-income-and-program-participation-sipp","implicit":true,"key":"Eu6xbSIFEw"},{"type":"paragraph","position":{"start":{"line":70,"column":1},"end":{"line":72,"column":1}},"children":[{"type":"text","value":"The SIPP provides income and program participation data. We use SIPP primarily to impute tip income\nthrough a Quantile Regression Forest model trained on SIPP data, using employment income, age, and\nhousehold composition as predictors.","position":{"start":{"line":70,"column":1},"end":{"line":70,"column":1}},"key":"QK0dvhtLhd"}],"key":"vjQOTu0m3C"},{"type":"heading","depth":3,"position":{"start":{"line":74,"column":1},"end":{"line":74,"column":1}},"children":[{"type":"text","value":"Survey of Consumer Finances (SCF)","position":{"start":{"line":74,"column":1},"end":{"line":74,"column":1}},"key":"bxHvmI6Xyj"}],"identifier":"survey-of-consumer-finances-scf","label":"Survey of Consumer Finances (SCF)","html_id":"survey-of-consumer-finances-scf","implicit":true,"key":"vAUxegfkRi"},{"type":"paragraph","position":{"start":{"line":76,"column":1},"end":{"line":80,"column":1}},"children":[{"type":"text","value":"The SCF provides wealth and debt information that we use to impute several financial variables\nmissing from the CPS. We match auto loan balances based on household demographics and income, then\ncalculate interest on auto loans from these imputed balances. Additionally, we impute various net\nworth components and other wealth measures not available in CPS. The SCF imputation uses their\nreference person definition to ensure proper matching.","position":{"start":{"line":76,"column":1},"end":{"line":76,"column":1}},"key":"gKEdDm6Eyv"}],"key":"MEeXOyx1zY"},{"type":"heading","depth":3,"position":{"start":{"line":82,"column":1},"end":{"line":82,"column":1}},"children":[{"type":"text","value":"American Community Survey (ACS)","position":{"start":{"line":82,"column":1},"end":{"line":82,"column":1}},"key":"nMYp8yEzUd"}],"identifier":"american-community-survey-acs","label":"American Community Survey (ACS)","html_id":"american-community-survey-acs","implicit":true,"key":"UNEg7gBLtg"},{"type":"paragraph","position":{"start":{"line":84,"column":1},"end":{"line":89,"column":1}},"children":[{"type":"text","value":"The ACS provides housing and geographic data that supplements the CPS housing information. For\nhomeowners, we impute property taxes based on state of residence, household income, and demographic\ncharacteristics. We also impute rent values for specific tenure types where CPS data is incomplete,\nalong with additional housing characteristics not captured in the CPS. These imputations use\nQuantile Regression Forests to preserve distributional characteristics while accounting for\nhousehold heterogeneity.","position":{"start":{"line":84,"column":1},"end":{"line":84,"column":1}},"key":"UiCWdFQdfo"}],"key":"lYg9Vqaign"},{"type":"heading","depth":2,"position":{"start":{"line":91,"column":1},"end":{"line":91,"column":1}},"children":[{"type":"text","value":"Calibration Data Sources","position":{"start":{"line":91,"column":1},"end":{"line":91,"column":1}},"key":"fCdHjbLuFE"}],"identifier":"calibration-data-sources","label":"Calibration Data Sources","html_id":"calibration-data-sources","implicit":true,"key":"UdoCjAaDML"},{"type":"paragraph","position":{"start":{"line":93,"column":1},"end":{"line":93,"column":1}},"children":[{"type":"text","value":"The calibration process uses targets from six administrative sources:","position":{"start":{"line":93,"column":1},"end":{"line":93,"column":1}},"key":"iQMzYMOoGk"}],"key":"s86WcoIfMu"},{"type":"heading","depth":3,"position":{"start":{"line":95,"column":1},"end":{"line":95,"column":1}},"children":[{"type":"text","value":"IRS Statistics of Income (SOI)","position":{"start":{"line":95,"column":1},"end":{"line":95,"column":1}},"key":"JTmHHgyRU1"}],"identifier":"irs-statistics-of-income-soi","label":"IRS Statistics of Income (SOI)","html_id":"irs-statistics-of-income-soi","implicit":true,"key":"ZwUqhhtplf"},{"type":"paragraph","position":{"start":{"line":97,"column":1},"end":{"line":98,"column":1}},"children":[{"type":"text","value":"The IRS SOI provides tax return aggregates by income level, filing status, and geography. These\ninclude counts of returns, aggregate income by source, deduction amounts, and credit utilization.","position":{"start":{"line":97,"column":1},"end":{"line":97,"column":1}},"key":"ge0ttb7on2"}],"key":"MTblNRxecl"},{"type":"heading","depth":3,"position":{"start":{"line":100,"column":1},"end":{"line":100,"column":1}},"children":[{"type":"text","value":"Census Population Estimates","position":{"start":{"line":100,"column":1},"end":{"line":100,"column":1}},"key":"vwc6Du0EdL"}],"identifier":"census-population-estimates","label":"Census Population Estimates","html_id":"census-population-estimates","implicit":true,"key":"uDq559EKOU"},{"type":"paragraph","position":{"start":{"line":102,"column":1},"end":{"line":102,"column":1}},"children":[{"type":"text","value":"Census provides population counts by age, state, and other demographic characteristics.","position":{"start":{"line":102,"column":1},"end":{"line":102,"column":1}},"key":"UgbBt99l1G"}],"key":"M2FSn1jv2o"},{"type":"heading","depth":3,"position":{"start":{"line":104,"column":1},"end":{"line":104,"column":1}},"children":[{"type":"text","value":"Congressional Budget Office","position":{"start":{"line":104,"column":1},"end":{"line":104,"column":1}},"key":"B27DZ6doxv"}],"identifier":"congressional-budget-office","label":"Congressional Budget Office","html_id":"congressional-budget-office","implicit":true,"key":"xvToi6YuDU"},{"type":"paragraph","position":{"start":{"line":106,"column":1},"end":{"line":107,"column":1}},"children":[{"type":"text","value":"CBO provides projections for program participation and spending, including SNAP benefits,\nunemployment compensation, and tax revenues.","position":{"start":{"line":106,"column":1},"end":{"line":106,"column":1}},"key":"lYeXSxXL1X"}],"key":"TGnpnUX3is"},{"type":"heading","depth":3,"position":{"start":{"line":109,"column":1},"end":{"line":109,"column":1}},"children":[{"type":"text","value":"Joint Committee on Taxation","position":{"start":{"line":109,"column":1},"end":{"line":109,"column":1}},"key":"drGiTYgGbk"}],"identifier":"joint-committee-on-taxation","label":"Joint Committee on Taxation","html_id":"joint-committee-on-taxation","implicit":true,"key":"qhfHZ662tj"},{"type":"paragraph","position":{"start":{"line":111,"column":1},"end":{"line":111,"column":1}},"children":[{"type":"text","value":"JCT provides estimates of tax expenditures for major deductions and credits.","position":{"start":{"line":111,"column":1},"end":{"line":111,"column":1}},"key":"Vi5Gd7Rz7s"}],"key":"ADqzfQ0prj"},{"type":"heading","depth":3,"position":{"start":{"line":113,"column":1},"end":{"line":113,"column":1}},"children":[{"type":"text","value":"Healthcare Spending Data","position":{"start":{"line":113,"column":1},"end":{"line":113,"column":1}},"key":"DPYHGHNecR"}],"identifier":"healthcare-spending-data","label":"Healthcare Spending Data","html_id":"healthcare-spending-data","implicit":true,"key":"DIOUrvM5KW"},{"type":"paragraph","position":{"start":{"line":115,"column":1},"end":{"line":116,"column":1}},"children":[{"type":"text","value":"Various sources provide data on health insurance premiums, Medicare costs, and medical spending by\nage group.","position":{"start":{"line":115,"column":1},"end":{"line":115,"column":1}},"key":"UqMltnl6G2"}],"key":"XSahsC5V6s"},{"type":"heading","depth":3,"position":{"start":{"line":118,"column":1},"end":{"line":118,"column":1}},"children":[{"type":"text","value":"State Administrative Data","position":{"start":{"line":118,"column":1},"end":{"line":118,"column":1}},"key":"ADUbTfspv6"}],"identifier":"state-administrative-data","label":"State Administrative Data","html_id":"state-administrative-data","implicit":true,"key":"FITuh9w6UF"},{"type":"paragraph","position":{"start":{"line":120,"column":1},"end":{"line":120,"column":1}},"children":[{"type":"text","value":"State-level program participation and spending data from various state agencies.","position":{"start":{"line":120,"column":1},"end":{"line":120,"column":1}},"key":"UTy6UaPJGy"}],"key":"CPdnorz5Ut"},{"type":"heading","depth":2,"position":{"start":{"line":122,"column":1},"end":{"line":122,"column":1}},"children":[{"type":"text","value":"Data Access and Documentation","position":{"start":{"line":122,"column":1},"end":{"line":122,"column":1}},"key":"uf42hT6oFq"}],"identifier":"data-access-and-documentation","label":"Data Access and Documentation","html_id":"data-access-and-documentation","implicit":true,"key":"Zn03LPr34s"},{"type":"paragraph","position":{"start":{"line":124,"column":1},"end":{"line":127,"column":1}},"children":[{"type":"text","value":"The enhanced dataset is publicly available through Hugging Face at\n","position":{"start":{"line":124,"column":1},"end":{"line":124,"column":1}},"key":"bytWQWUh3k"},{"type":"link","url":"https://huggingface.co/datasets/PolicyEngine/policyengine-us-data","position":{"start":{"line":124,"column":1},"end":{"line":124,"column":1}},"children":[{"type":"text","value":"https://​huggingface​.co​/datasets​/PolicyEngine​/policyengine​-us​-data","position":{"start":{"line":124,"column":1},"end":{"line":124,"column":1}},"key":"rW6he3ebUn"}],"urlSource":"https://huggingface.co/datasets/PolicyEngine/policyengine-us-data","key":"POR8QmxZpx"},{"type":"text","value":".\nWe distribute the data as HDF5 files compatible with PolicyEngine and other microsimulation\nframeworks, with new releases accompanying each CPS vintage.","position":{"start":{"line":124,"column":1},"end":{"line":124,"column":1}},"key":"c2hDoYswU2"}],"key":"qr5eNcJq6s"},{"type":"paragraph","position":{"start":{"line":129,"column":1},"end":{"line":130,"column":1}},"children":[{"type":"text","value":"We maintain complete documentation of variable definitions, imputation procedures, and calibration\ntargets in the project repository.","position":{"start":{"line":129,"column":1},"end":{"line":129,"column":1}},"key":"M0j5b4QYdP"}],"key":"zY7xnW7118"}],"key":"sKvJjD7U7M"}],"key":"KwODkgEFq4"},"references":{"cite":{"order":["rothbaum2021"],"data":{"rothbaum2021":{"label":"rothbaum2021","enumerator":"1","html":"Rothbaum, J., & Bee, A. (2021). Has Income Underreporting Changed Over Time? Evidence from Linked Survey and Administrative Data. <i>Journal of Business and Economic Statistics</i>, <i>39</i>(2), 456–475."}}}},"footer":{"navigation":{"prev":{"title":"Background","url":"/background","group":"PolicyEngine US Data"},"next":{"title":"Methodology","url":"/methodology","group":"PolicyEngine US Data"}}},"domain":"http://localhost:3000"}